mckit.libs/libiomp5-31023e22.so
mckit.libs/libmkl_core-9c1c93e0.so.2
mckit.libs/libmkl_intel_ilp64-b7ff0314.so.2
mckit.libs/libmkl_intel_thread-77a73fe9.so.2
mckit.libs/libnlopt-1cc25482.so.1.0.0
mckit/__init__.py
mckit/_init_dynamic_libraries.py
mckit/body.py
mckit/box.py
mckit/card.py
mckit/cli/__init__.py
mckit/cli/_logging.py
mckit/cli/commands/__init__.py
mckit/cli/commands/check.py
mckit/cli/commands/common.py
mckit/cli/commands/compose.py
mckit/cli/commands/decompose.py
mckit/cli/commands/split.py
mckit/cli/commands/transform.py
mckit/cli/runner.py
mckit/constants.py
mckit/data/isotopes.dat
mckit/fmesh.py
mckit/geometry.cpython-313-x86_64-linux-gnu.so
mckit/material.py
mckit/parser/__init__.py
mckit/parser/cell_parser.py
mckit/parser/common/__init__.py
mckit/parser/common/cell_index.py
mckit/parser/common/composition_index.py
mckit/parser/common/lexer.py
mckit/parser/common/surface_index.py
mckit/parser/common/transformation_index.py
mckit/parser/common/utils.py
mckit/parser/material_parser.py
mckit/parser/mcnp_input_sly_parser.py
mckit/parser/mcnp_section_parser.py
mckit/parser/mctal_parser.py
mckit/parser/meshtal_parser.py
mckit/parser/surface_parser.py
mckit/parser/transformation_parser.py
mckit/printer.py
mckit/source.py
mckit/src/box.c
mckit/src/box.h
mckit/src/box_doc.h
mckit/src/common.h
mckit/src/geometrymodule.c
mckit/src/rbtree.c
mckit/src/rbtree.h
mckit/src/shape.c
mckit/src/shape.h
mckit/src/surf_doc.h
mckit/src/surface.c
mckit/src/surface.h
mckit/surface.py
mckit/transformation.py
mckit/universe.py
mckit/utils/__init__.py
mckit/utils/_io.py
mckit/utils/_resource.py
mckit/utils/accept.py
mckit/utils/indexes.py
mckit/utils/misc.py
mckit/utils/named.py
mckit/utils/tolerance.py
mckit/version.py
mckit-0.8.6.dist-info/METADATA
mckit-0.8.6.dist-info/WHEEL
mckit-0.8.6.dist-info/entry_points.txt
mckit-0.8.6.dist-info/licenses/LICENSE
mckit-0.8.6.dist-info/RECORD
