Metadata-Version: 2.4
Name: mckit
Version: 0.8.6
Summary: Tools to process MCNP models and results
Keywords: mckit,MCNP
Author: rrn
Maintainer-Email: dvp2015 <dmitri_portnov@yahoo.com>
License-Expression: MIT
Classifier: Development Status :: 4 - Beta
Classifier: Environment :: Console
Classifier: Intended Audience :: Developers
Classifier: Intended Audience :: Science/Research
Classifier: Operating System :: Microsoft :: Windows
Classifier: Operating System :: POSIX :: Linux
Classifier: Programming Language :: C
Classifier: Programming Language :: Python :: 3
Classifier: Topic :: Scientific/Engineering :: Physics
Project-URL: Homepage, https://github.com/MC-kit/mckit
Project-URL: Repository, https://github.com/MC-kit/mckit
Project-URL: Documentation, https://mckit.readthedocs.io
Project-URL: Issues, https://github.com/MC-kit/mckit/issues
Requires-Python: >=3.12
Requires-Dist: attrs<26,>=25.3.0
Requires-Dist: click<9,>=8.2.1
Requires-Dist: loguru<0.8,>=0.7.3
Requires-Dist: mkl-devel<2026,>=2025.2.0
Requires-Dist: numpy
Requires-Dist: ply<4,>=3.11
Requires-Dist: python-dotenv<2,>=1.1.1
Requires-Dist: sly<0.6,>=0.5
Requires-Dist: tomli-w<2,>=1.2.0
Requires-Dist: tqdm<5,>=4.67.1
Requires-Dist: typer<0.17,>=0.16.1
